{
  "districtCode": "LK",
  "type": "presidential",
  "nullVotes": 0,
  "constituencies": [
    {
      "code": "038",
      "isLegacy": false,
      "candidates": [
        {
          "candidateCode": "LAZCHA",
          "partyCode": "UNKNOWN",
          "votes": 2981
        },
        {
          "candidateCode": "PETKUW",
          "partyCode": "UNKNOWN",
          "votes": 37
        },
        {
          "candidateCode": "PETMUT",
          "partyCode": "UNKNOWN",
          "votes": 1690
        },
        {
          "candidateCode": "LAZCHA",
          "partyCode": "UNKNOWN",
          "votes": 6044
        }
      ]
    },
    {
      "code": "038",
      "isLegacy": false,
      "candidates": [
        {
          "candidateCode": "LAZCHA",
          "partyCode": "UNKNOWN",
          "votes": 2981
        },
        {
          "candidateCode": "PETKUW",
          "partyCode": "UNKNOWN",
          "votes": 37
        },
        {
          "candidateCode": "PETMUT",
          "partyCode": "UNKNOWN",
          "votes": 1690
        },
        {
          "candidateCode": "LAZCHA",
          "partyCode": "UNKNOWN",
          "votes": 6044
        }
      ]
    }
  ]
}