{
  "districtCode": "MG",
  "type": "presidential",
  "nullVotes": 6216,
  "constituencies": [
    {
      "code": "132",
      "isLegacy": false,
      "candidates": [
        {
          "candidateCode": "ARTMUT",
          "partyCode": "DPP",
          "votes": 3223
        },
        {
          "candidateCode": "LAZCHA",
          "partyCode": "MCP",
          "votes": 65380
        },
        {
          "candidateCode": "PETKUW",
          "partyCode": "MMD",
          "votes": 278
        }
      ]
    },
    {
      "code": "133",
      "isLegacy": false,
      "candidates": [
        {
          "candidateCode": "ARTMUT",
          "partyCode": "DPP",
          "votes": 1419
        },
        {
          "candidateCode": "LAZCHA",
          "partyCode": "MCP",
          "votes": 63228
        },
        {
          "candidateCode": "PETKUW",
          "partyCode": "MMD",
          "votes": 101
        }
      ]
    },
    {
      "code": "134",
      "isLegacy": false,
      "candidates": [
        {
          "candidateCode": "ARTMUT",
          "partyCode": "DPP",
          "votes": 3745
        },
        {
          "candidateCode": "LAZCHA",
          "partyCode": "MCP",
          "votes": 33587
        },
        {
          "candidateCode": "PETKUW",
          "partyCode": "MMD",
          "votes": 147
        }
      ]
    },
    {
      "code": "135",
      "isLegacy": false,
      "candidates": [
        {
          "candidateCode": "ARTMUT",
          "partyCode": "DPP",
          "votes": 5606
        },
        {
          "candidateCode": "LAZCHA",
          "partyCode": "MCP",
          "votes": 69798
        },
        {
          "candidateCode": "PETKUW",
          "partyCode": "MMD",
          "votes": 261
        }
      ]
    },
    {
      "code": "136",
      "isLegacy": true,
      "candidates": []
    },
    {
      "code": "137",
      "isLegacy": true,
      "candidates": []
    },
    {
      "code": "138",
      "isLegacy": true,
      "candidates": []
    },
    {
      "code": "139",
      "isLegacy": true,
      "candidates": []
    },
    {
      "code": "140",
      "isLegacy": false,
      "candidates": [
        {
          "candidateCode": "ARTMUT",
          "partyCode": "DPP",
          "votes": 5583
        },
        {
          "candidateCode": "LAZCHA",
          "partyCode": "MCP",
          "votes": 68644
        },
        {
          "candidateCode": "PETKUW",
          "partyCode": "MMD",
          "votes": 536
        }
      ]
    },
    {
      "code": "141",
      "isLegacy": false,
      "candidates": [
        {
          "candidateCode": "ARTMUT",
          "partyCode": "DPP",
          "votes": 5830
        },
        {
          "candidateCode": "LAZCHA",
          "partyCode": "MCP",
          "votes": 51042
        },
        {
          "candidateCode": "PETKUW",
          "partyCode": "MMD",
          "votes": 539
        }
      ]
    },
    {
      "code": "142",
      "isLegacy": false,
      "candidates": [
        {
          "candidateCode": "ARTMUT",
          "partyCode": "DPP",
          "votes": 2047
        },
        {
          "candidateCode": "LAZCHA",
          "partyCode": "MCP",
          "votes": 30754
        },
        {
          "candidateCode": "PETKUW",
          "partyCode": "MMD",
          "votes": 269
        }
      ]
    },
    {
      "code": "143",
      "isLegacy": true,
      "candidates": []
    },
    {
      "code": "144",
      "isLegacy": true,
      "candidates": []
    }
  ]
}