{
  "districtCode": "NK",
  "type": "presidential",
  "nullVotes": 658,
  "constituencies": [
    {
      "code": "039",
      "isLegacy": false,
      "candidates": [
        {
          "candidateCode": "ARTMUT",
          "partyCode": "DPP",
          "votes": 680
        },
        {
          "candidateCode": "LAZCHA",
          "partyCode": "MCP",
          "votes": 6250
        },
        {
          "candidateCode": "PETKUW",
          "partyCode": "MMD",
          "votes": 58
        }
      ]
    },
    {
      "code": "040",
      "isLegacy": false,
      "candidates": [
        {
          "candidateCode": "ARTMUT",
          "partyCode": "DPP",
          "votes": 8535
        },
        {
          "candidateCode": "LAZCHA",
          "partyCode": "MCP",
          "votes": 26112
        },
        {
          "candidateCode": "PETKUW",
          "partyCode": "MMD",
          "votes": 344
        }
      ]
    },
    {
      "code": "041",
      "isLegacy": false,
      "candidates": [
        {
          "candidateCode": "ARTMUT",
          "partyCode": "DPP",
          "votes": 2420
        },
        {
          "candidateCode": "LAZCHA",
          "partyCode": "MCP",
          "votes": 10444
        },
        {
          "candidateCode": "PETKUW",
          "partyCode": "MMD",
          "votes": 113
        }
      ]
    },
    {
      "code": "042",
      "isLegacy": false,
      "candidates": [
        {
          "candidateCode": "ARTMUT",
          "partyCode": "DPP",
          "votes": 680
        },
        {
          "candidateCode": "LAZCHA",
          "partyCode": "MCP",
          "votes": 6250
        },
        {
          "candidateCode": "PETKUW",
          "partyCode": "MMD",
          "votes": 58
        }
      ]
    },
    {
      "code": "043",
      "isLegacy": false,
      "candidates": [
        {
          "candidateCode": "ARTMUT",
          "partyCode": "DPP",
          "votes": 680
        },
        {
          "candidateCode": "LAZCHA",
          "partyCode": "MCP",
          "votes": 6250
        },
        {
          "candidateCode": "PETKUW",
          "partyCode": "MMD",
          "votes": 58
        }
      ]
    }
  ]
}