{
  "districtCode": "NU",
  "type": "presidential",
  "nullVotes": 0,
  "constituencies": [
    {
      "code": "124",
      "isLegacy": false,
      "candidates": [
        {
          "candidateCode": "LAZCHA",
          "partyCode": "UNKNOWN",
          "votes": 16737
        },
        {
          "candidateCode": "PETKUW",
          "partyCode": "UNKNOWN",
          "votes": 612
        },
        {
          "candidateCode": "PETMUT",
          "partyCode": "UNKNOWN",
          "votes": 2553
        },
        {
          "candidateCode": "LAZCHA",
          "partyCode": "UNKNOWN",
          "votes": 11297
        }
      ]
    },
    {
      "code": "125",
      "isLegacy": false,
      "candidates": [
        {
          "candidateCode": "LAZCHA",
          "partyCode": "UNKNOWN",
          "votes": 11297
        },
        {
          "candidateCode": "PETKUW",
          "partyCode": "UNKNOWN",
          "votes": 301
        },
        {
          "candidateCode": "PETMUT",
          "partyCode": "UNKNOWN",
          "votes": 2405
        },
        {
          "candidateCode": "LAZCHA",
          "partyCode": "UNKNOWN",
          "votes": 4508
        }
      ]
    },
    {
      "code": "128",
      "isLegacy": false,
      "candidates": [
        {
          "candidateCode": "LAZCHA",
          "partyCode": "UNKNOWN",
          "votes": 17629
        },
        {
          "candidateCode": "PETKUW",
          "partyCode": "UNKNOWN",
          "votes": 375
        },
        {
          "candidateCode": "PETMUT",
          "partyCode": "UNKNOWN",
          "votes": 3574
        },
        {
          "candidateCode": "LAZCHA",
          "partyCode": "UNKNOWN",
          "votes": 8077
        }
      ]
    },
    {
      "code": "131",
      "isLegacy": false,
      "candidates": [
        {
          "candidateCode": "LAZCHA",
          "partyCode": "UNKNOWN",
          "votes": 8077
        },
        {
          "candidateCode": "PETKUW",
          "partyCode": "UNKNOWN",
          "votes": 301
        },
        {
          "candidateCode": "PETMUT",
          "partyCode": "UNKNOWN",
          "votes": 4724
        },
        {
          "candidateCode": "LAZCHA",
          "partyCode": "UNKNOWN",
          "votes": 10331
        }
      ]
    },
    {
      "code": "131",
      "isLegacy": false,
      "candidates": [
        {
          "candidateCode": "LAZCHA",
          "partyCode": "UNKNOWN",
          "votes": 8077
        },
        {
          "candidateCode": "PETKUW",
          "partyCode": "UNKNOWN",
          "votes": 301
        },
        {
          "candidateCode": "PETMUT",
          "partyCode": "UNKNOWN",
          "votes": 4724
        },
        {
          "candidateCode": "LAZCHA",
          "partyCode": "UNKNOWN",
          "votes": 10331
        }
      ]
    }
  ]
}