{
  "districtCode": "LI",
  "type": "presidential",
  "nullVotes": 76,
  "constituencies": [
    {
      "code": "084",
      "isLegacy": false,
      "candidates": [
        {
          "candidateCode": "PETMUT",
          "partyCode": "DPP",
          "votes": 905
        },
        {
          "candidateCode": "ATUMUL",
          "partyCode": "UDF",
          "votes": 699
        },
        {
          "candidateCode": "LAZCHA",
          "partyCode": "MCP",
          "votes": 1108
        },
        {
          "candidateCode": "JOYBAN",
          "partyCode": "PP",
          "votes": 600
        },
        {
          "candidateCode": "SAUCHI",
          "partyCode": "UTM",
          "votes": 684
        }
      ]
    },
    {
      "code": "085",
      "isLegacy": false,
      "candidates": [
        {
          "candidateCode": "PETMUT",
          "partyCode": "DPP",
          "votes": 717
        },
        {
          "candidateCode": "ATUMUL",
          "partyCode": "UDF",
          "votes": 767
        },
        {
          "candidateCode": "LAZCHA",
          "partyCode": "MCP",
          "votes": 1074
        },
        {
          "candidateCode": "JOYBAN",
          "partyCode": "PP",
          "votes": 598
        },
        {
          "candidateCode": "SAUCHI",
          "partyCode": "UTM",
          "votes": 812
        }
      ]
    },
    {
      "code": "086",
      "isLegacy": false,
      "candidates": [
        {
          "candidateCode": "PETMUT",
          "partyCode": "DPP",
          "votes": 830
        },
        {
          "candidateCode": "ATUMUL",
          "partyCode": "UDF",
          "votes": 744
        },
        {
          "candidateCode": "LAZCHA",
          "partyCode": "MCP",
          "votes": 1088
        },
        {
          "candidateCode": "JOYBAN",
          "partyCode": "PP",
          "votes": 625
        },
        {
          "candidateCode": "SAUCHI",
          "partyCode": "UTM",
          "votes": 847
        }
      ]
    },
    {
      "code": "087",
      "isLegacy": false,
      "candidates": [
        {
          "candidateCode": "PETMUT",
          "partyCode": "DPP",
          "votes": 864
        },
        {
          "candidateCode": "ATUMUL",
          "partyCode": "UDF",
          "votes": 825
        },
        {
          "candidateCode": "LAZCHA",
          "partyCode": "MCP",
          "votes": 1153
        },
        {
          "candidateCode": "JOYBAN",
          "partyCode": "PP",
          "votes": 605
        },
        {
          "candidateCode": "SAUCHI",
          "partyCode": "UTM",
          "votes": 865
        }
      ]
    },
    {
      "code": "088",
      "isLegacy": false,
      "candidates": [
        {
          "candidateCode": "PETMUT",
          "partyCode": "DPP",
          "votes": 770
        },
        {
          "candidateCode": "ATUMUL",
          "partyCode": "UDF",
          "votes": 777
        },
        {
          "candidateCode": "LAZCHA",
          "partyCode": "MCP",
          "votes": 1026
        },
        {
          "candidateCode": "JOYBAN",
          "partyCode": "PP",
          "votes": 577
        },
        {
          "candidateCode": "SAUCHI",
          "partyCode": "UTM",
          "votes": 691
        }
      ]
    },
    {
      "code": "089",
      "isLegacy": false,
      "candidates": [
        {
          "candidateCode": "PETMUT",
          "partyCode": "DPP",
          "votes": 897
        },
        {
          "candidateCode": "ATUMUL",
          "partyCode": "UDF",
          "votes": 781
        },
        {
          "candidateCode": "LAZCHA",
          "partyCode": "MCP",
          "votes": 1005
        },
        {
          "candidateCode": "JOYBAN",
          "partyCode": "PP",
          "votes": 645
        },
        {
          "candidateCode": "SAUCHI",
          "partyCode": "UTM",
          "votes": 767
        }
      ]
    },
    {
      "code": "090",
      "isLegacy": false,
      "candidates": [
        {
          "candidateCode": "PETMUT",
          "partyCode": "DPP",
          "votes": 913
        },
        {
          "candidateCode": "ATUMUL",
          "partyCode": "UDF",
          "votes": 806
        },
        {
          "candidateCode": "LAZCHA",
          "partyCode": "MCP",
          "votes": 1015
        },
        {
          "candidateCode": "JOYBAN",
          "partyCode": "PP",
          "votes": 678
        },
        {
          "candidateCode": "SAUCHI",
          "partyCode": "UTM",
          "votes": 838
        }
      ]
    },
    {
      "code": "091",
      "isLegacy": false,
      "candidates": [
        {
          "candidateCode": "PETMUT",
          "partyCode": "DPP",
          "votes": 830
        },
        {
          "candidateCode": "ATUMUL",
          "partyCode": "UDF",
          "votes": 807
        },
        {
          "candidateCode": "LAZCHA",
          "partyCode": "MCP",
          "votes": 1156
        },
        {
          "candidateCode": "JOYBAN",
          "partyCode": "PP",
          "votes": 641
        },
        {
          "candidateCode": "SAUCHI",
          "partyCode": "UTM",
          "votes": 761
        }
      ]
    },
    {
      "code": "092",
      "isLegacy": false,
      "candidates": [
        {
          "candidateCode": "PETMUT",
          "partyCode": "DPP",
          "votes": 755
        },
        {
          "candidateCode": "ATUMUL",
          "partyCode": "UDF",
          "votes": 767
        },
        {
          "candidateCode": "LAZCHA",
          "partyCode": "MCP",
          "votes": 1092
        },
        {
          "candidateCode": "JOYBAN",
          "partyCode": "PP",
          "votes": 494
        },
        {
          "candidateCode": "SAUCHI",
          "partyCode": "UTM",
          "votes": 854
        }
      ]
    },
    {
      "code": "093",
      "isLegacy": false,
      "candidates": [
        {
          "candidateCode": "PETMUT",
          "partyCode": "DPP",
          "votes": 775
        },
        {
          "candidateCode": "ATUMUL",
          "partyCode": "UDF",
          "votes": 814
        },
        {
          "candidateCode": "LAZCHA",
          "partyCode": "MCP",
          "votes": 1015
        },
        {
          "candidateCode": "JOYBAN",
          "partyCode": "PP",
          "votes": 665
        },
        {
          "candidateCode": "SAUCHI",
          "partyCode": "UTM",
          "votes": 818
        }
      ]
    },
    {
      "code": "094",
      "isLegacy": false,
      "candidates": [
        {
          "candidateCode": "PETMUT",
          "partyCode": "DPP",
          "votes": 717
        },
        {
          "candidateCode": "ATUMUL",
          "partyCode": "UDF",
          "votes": 841
        },
        {
          "candidateCode": "LAZCHA",
          "partyCode": "MCP",
          "votes": 1002
        },
        {
          "candidateCode": "JOYBAN",
          "partyCode": "PP",
          "votes": 562
        },
        {
          "candidateCode": "SAUCHI",
          "partyCode": "UTM",
          "votes": 774
        }
      ]
    },
    {
      "code": "095",
      "isLegacy": false,
      "candidates": [
        {
          "candidateCode": "PETMUT",
          "partyCode": "DPP",
          "votes": 822
        },
        {
          "candidateCode": "ATUMUL",
          "partyCode": "UDF",
          "votes": 747
        },
        {
          "candidateCode": "LAZCHA",
          "partyCode": "MCP",
          "votes": 1017
        },
        {
          "candidateCode": "JOYBAN",
          "partyCode": "PP",
          "votes": 562
        },
        {
          "candidateCode": "SAUCHI",
          "partyCode": "UTM",
          "votes": 820
        }
      ]
    },
    {
      "code": "096",
      "isLegacy": false,
      "candidates": [
        {
          "candidateCode": "PETMUT",
          "partyCode": "DPP",
          "votes": 748
        },
        {
          "candidateCode": "ATUMUL",
          "partyCode": "UDF",
          "votes": 740
        },
        {
          "candidateCode": "LAZCHA",
          "partyCode": "MCP",
          "votes": 1085
        },
        {
          "candidateCode": "JOYBAN",
          "partyCode": "PP",
          "votes": 488
        },
        {
          "candidateCode": "SAUCHI",
          "partyCode": "UTM",
          "votes": 866
        }
      ]
    },
    {
      "code": "097",
      "isLegacy": false,
      "candidates": [
        {
          "candidateCode": "PETMUT",
          "partyCode": "DPP",
          "votes": 903
        },
        {
          "candidateCode": "ATUMUL",
          "partyCode": "UDF",
          "votes": 672
        },
        {
          "candidateCode": "LAZCHA",
          "partyCode": "MCP",
          "votes": 1133
        },
        {
          "candidateCode": "JOYBAN",
          "partyCode": "PP",
          "votes": 524
        },
        {
          "candidateCode": "SAUCHI",
          "partyCode": "UTM",
          "votes": 803
        }
      ]
    },
    {
      "code": "098",
      "isLegacy": false,
      "candidates": [
        {
          "candidateCode": "PETMUT",
          "partyCode": "DPP",
          "votes": 733
        },
        {
          "candidateCode": "ATUMUL",
          "partyCode": "UDF",
          "votes": 666
        },
        {
          "candidateCode": "LAZCHA",
          "partyCode": "MCP",
          "votes": 1110
        },
        {
          "candidateCode": "JOYBAN",
          "partyCode": "PP",
          "votes": 612
        },
        {
          "candidateCode": "SAUCHI",
          "partyCode": "UTM",
          "votes": 756
        }
      ]
    },
    {
      "code": "099",
      "isLegacy": false,
      "candidates": [
        {
          "candidateCode": "PETMUT",
          "partyCode": "DPP",
          "votes": 813
        },
        {
          "candidateCode": "ATUMUL",
          "partyCode": "UDF",
          "votes": 779
        },
        {
          "candidateCode": "LAZCHA",
          "partyCode": "MCP",
          "votes": 1095
        },
        {
          "candidateCode": "JOYBAN",
          "partyCode": "PP",
          "votes": 573
        },
        {
          "candidateCode": "SAUCHI",
          "partyCode": "UTM",
          "votes": 825
        }
      ]
    },
    {
      "code": "100",
      "isLegacy": false,
      "candidates": [
        {
          "candidateCode": "PETMUT",
          "partyCode": "DPP",
          "votes": 738
        },
        {
          "candidateCode": "ATUMUL",
          "partyCode": "UDF",
          "votes": 848
        },
        {
          "candidateCode": "LAZCHA",
          "partyCode": "MCP",
          "votes": 1083
        },
        {
          "candidateCode": "JOYBAN",
          "partyCode": "PP",
          "votes": 500
        },
        {
          "candidateCode": "SAUCHI",
          "partyCode": "UTM",
          "votes": 772
        }
      ]
    },
    {
      "code": "101",
      "isLegacy": false,
      "candidates": [
        {
          "candidateCode": "PETMUT",
          "partyCode": "DPP",
          "votes": 848
        },
        {
          "candidateCode": "ATUMUL",
          "partyCode": "UDF",
          "votes": 778
        },
        {
          "candidateCode": "LAZCHA",
          "partyCode": "MCP",
          "votes": 1133
        },
        {
          "candidateCode": "JOYBAN",
          "partyCode": "PP",
          "votes": 607
        },
        {
          "candidateCode": "SAUCHI",
          "partyCode": "UTM",
          "votes": 815
        }
      ]
    },
    {
      "code": "102",
      "isLegacy": false,
      "candidates": [
        {
          "candidateCode": "PETMUT",
          "partyCode": "DPP",
          "votes": 728
        },
        {
          "candidateCode": "ATUMUL",
          "partyCode": "UDF",
          "votes": 826
        },
        {
          "candidateCode": "LAZCHA",
          "partyCode": "MCP",
          "votes": 1134
        },
        {
          "candidateCode": "JOYBAN",
          "partyCode": "PP",
          "votes": 546
        },
        {
          "candidateCode": "SAUCHI",
          "partyCode": "UTM",
          "votes": 843
        }
      ]
    },
    {
      "code": "103",
      "isLegacy": false,
      "candidates": [
        {
          "candidateCode": "PETMUT",
          "partyCode": "DPP",
          "votes": 772
        },
        {
          "candidateCode": "ATUMUL",
          "partyCode": "UDF",
          "votes": 719
        },
        {
          "candidateCode": "LAZCHA",
          "partyCode": "MCP",
          "votes": 1116
        },
        {
          "candidateCode": "JOYBAN",
          "partyCode": "PP",
          "votes": 528
        },
        {
          "candidateCode": "SAUCHI",
          "partyCode": "UTM",
          "votes": 760
        }
      ]
    },
    {
      "code": "104",
      "isLegacy": false,
      "candidates": [
        {
          "candidateCode": "PETMUT",
          "partyCode": "DPP",
          "votes": 767
        },
        {
          "candidateCode": "ATUMUL",
          "partyCode": "UDF",
          "votes": 714
        },
        {
          "candidateCode": "LAZCHA",
          "partyCode": "MCP",
          "votes": 981
        },
        {
          "candidateCode": "JOYBAN",
          "partyCode": "PP",
          "votes": 621
        },
        {
          "candidateCode": "SAUCHI",
          "partyCode": "UTM",
          "votes": 763
        }
      ]
    },
    {
      "code": "105",
      "isLegacy": false,
      "candidates": [
        {
          "candidateCode": "PETMUT",
          "partyCode": "DPP",
          "votes": 831
        },
        {
          "candidateCode": "ATUMUL",
          "partyCode": "UDF",
          "votes": 810
        },
        {
          "candidateCode": "LAZCHA",
          "partyCode": "MCP",
          "votes": 1007
        },
        {
          "candidateCode": "JOYBAN",
          "partyCode": "PP",
          "votes": 604
        },
        {
          "candidateCode": "SAUCHI",
          "partyCode": "UTM",
          "votes": 768
        }
      ]
    },
    {
      "code": "106",
      "isLegacy": false,
      "candidates": [
        {
          "candidateCode": "PETMUT",
          "partyCode": "DPP",
          "votes": 851
        },
        {
          "candidateCode": "ATUMUL",
          "partyCode": "UDF",
          "votes": 713
        },
        {
          "candidateCode": "LAZCHA",
          "partyCode": "MCP",
          "votes": 971
        },
        {
          "candidateCode": "JOYBAN",
          "partyCode": "PP",
          "votes": 605
        },
        {
          "candidateCode": "SAUCHI",
          "partyCode": "UTM",
          "votes": 840
        }
      ]
    },
    {
      "code": "107",
      "isLegacy": false,
      "candidates": [
        {
          "candidateCode": "PETMUT",
          "partyCode": "DPP",
          "votes": 738
        },
        {
          "candidateCode": "ATUMUL",
          "partyCode": "UDF",
          "votes": 688
        },
        {
          "candidateCode": "LAZCHA",
          "partyCode": "MCP",
          "votes": 966
        },
        {
          "candidateCode": "JOYBAN",
          "partyCode": "PP",
          "votes": 640
        },
        {
          "candidateCode": "SAUCHI",
          "partyCode": "UTM",
          "votes": 747
        }
      ]
    },
    {
      "code": "108",
      "isLegacy": false,
      "candidates": [
        {
          "candidateCode": "PETMUT",
          "partyCode": "DPP",
          "votes": 773
        },
        {
          "candidateCode": "ATUMUL",
          "partyCode": "UDF",
          "votes": 754
        },
        {
          "candidateCode": "LAZCHA",
          "partyCode": "MCP",
          "votes": 1079
        },
        {
          "candidateCode": "JOYBAN",
          "partyCode": "PP",
          "votes": 486
        },
        {
          "candidateCode": "SAUCHI",
          "partyCode": "UTM",
          "votes": 678
        }
      ]
    },
    {
      "code": "109",
      "isLegacy": false,
      "candidates": [
        {
          "candidateCode": "PETMUT",
          "partyCode": "DPP",
          "votes": 832
        },
        {
          "candidateCode": "ATUMUL",
          "partyCode": "UDF",
          "votes": 747
        },
        {
          "candidateCode": "LAZCHA",
          "partyCode": "MCP",
          "votes": 979
        },
        {
          "candidateCode": "JOYBAN",
          "partyCode": "PP",
          "votes": 548
        },
        {
          "candidateCode": "SAUCHI",
          "partyCode": "UTM",
          "votes": 802
        }
      ]
    },
    {
      "code": "110",
      "isLegacy": false,
      "candidates": [
        {
          "candidateCode": "PETMUT",
          "partyCode": "DPP",
          "votes": 838
        },
        {
          "candidateCode": "ATUMUL",
          "partyCode": "UDF",
          "votes": 843
        },
        {
          "candidateCode": "LAZCHA",
          "partyCode": "MCP",
          "votes": 1144
        },
        {
          "candidateCode": "JOYBAN",
          "partyCode": "PP",
          "votes": 677
        },
        {
          "candidateCode": "SAUCHI",
          "partyCode": "UTM",
          "votes": 737
        }
      ]
    },
    {
      "code": "111",
      "isLegacy": false,
      "candidates": [
        {
          "candidateCode": "PETMUT",
          "partyCode": "DPP",
          "votes": 798
        },
        {
          "candidateCode": "ATUMUL",
          "partyCode": "UDF",
          "votes": 763
        },
        {
          "candidateCode": "LAZCHA",
          "partyCode": "MCP",
          "votes": 1102
        },
        {
          "candidateCode": "JOYBAN",
          "partyCode": "PP",
          "votes": 627
        },
        {
          "candidateCode": "SAUCHI",
          "partyCode": "UTM",
          "votes": 690
        }
      ]
    },
    {
      "code": "112",
      "isLegacy": false,
      "candidates": [
        {
          "candidateCode": "PETMUT",
          "partyCode": "DPP",
          "votes": 910
        },
        {
          "candidateCode": "ATUMUL",
          "partyCode": "UDF",
          "votes": 846
        },
        {
          "candidateCode": "LAZCHA",
          "partyCode": "MCP",
          "votes": 1081
        },
        {
          "candidateCode": "JOYBAN",
          "partyCode": "PP",
          "votes": 592
        },
        {
          "candidateCode": "SAUCHI",
          "partyCode": "UTM",
          "votes": 696
        }
      ]
    },
    {
      "code": "113",
      "isLegacy": false,
      "candidates": [
        {
          "candidateCode": "PETMUT",
          "partyCode": "DPP",
          "votes": 751
        },
        {
          "candidateCode": "ATUMUL",
          "partyCode": "UDF",
          "votes": 738
        },
        {
          "candidateCode": "LAZCHA",
          "partyCode": "MCP",
          "votes": 1004
        },
        {
          "candidateCode": "JOYBAN",
          "partyCode": "PP",
          "votes": 598
        },
        {
          "candidateCode": "SAUCHI",
          "partyCode": "UTM",
          "votes": 815
        }
      ]
    }
  ]
}